README.md
setup.py
samplexrsasasasasd/__init__.py
samplexrsasasasasd/samplexrsas.py
samplexrsasasasasd.egg-info/PKG-INFO
samplexrsasasasasd.egg-info/SOURCES.txt
samplexrsasasasasd.egg-info/dependency_links.txt
samplexrsasasasasd.egg-info/requires.txt
samplexrsasasasasd.egg-info/top_level.txt